straw_machine/__init__.py
straw_machine/dataclass/__init__.py
straw_machine/dataclass/_estimator.py
straw_machine/dataclass/_transformer.py
straw_machine/gallery/__init__.py
straw_machine/gallery/date.py
straw_machine/util/__init__.py
straw_machine/util/_generate.py
straw_machine-0.0.3.dist-info/LICENSE
straw_machine-0.0.3.dist-info/METADATA
straw_machine-0.0.3.dist-info/WHEEL
straw_machine-0.0.3.dist-info/top_level.txt
straw_machine-0.0.3.dist-info/RECORD
