Metadata-Version: 2.1
Name: straw-machine
Version: 0.0.3
Summary: A python making machine of sklearn pipeline
Home-page: https://github.com/blizhan/straw-machine
Author: blizhan
Author-email: blizhan@icloud.com
Classifier: Programming Language :: Python :: 3
Requires-Python: >=3.8
License-File: LICENSE
Requires-Dist: scikit-learn (>=1.2.1)
Requires-Dist: pandas
Requires-Dist: cloudpickle
